{
  "totals": {
    "checked": 31,
    "foundOnSteam": 11,
    "confidentMatches": 11,
    "confidentDlc": 2,
    "confidentGame": 9
  },
  "confidentDlc": [
    {
      "title": "Civilization VI: Rise and Fall",
      "steamName": "Sid Meier’s Civilization® VI: Rise and Fall",
      "appid": 645402,
      "url": "https://store.steampowered.com/app/645402/"
    },
    {
      "title": "Halo 3 ODST",
      "steamName": "Halo 3: ODST",
      "appid": 1064272,
      "url": "https://store.steampowered.com/app/1064272/"
    }
  ],
  "confidentGame": [
    {
      "title": "Company of Heroes: Tales of Valor",
      "steamName": "Company of Heroes: Tales of Valor",
      "appid": 20540,
      "url": "https://store.steampowered.com/app/20540/"
    },
    {
      "title": "Crossfire",
      "steamName": "Critter Crossfire",
      "appid": 2644230,
      "url": "https://store.steampowered.com/app/2644230/"
    },
    {
      "title": "Delta Force: Task Force Dagger",
      "steamName": "Delta Force: Task Force Dagger",
      "appid": 32650,
      "url": "https://store.steampowered.com/app/32650/"
    },
    {
      "title": "Dishonored Death of the Outsider",
      "steamName": "Dishonored®: Death of the Outsider™",
      "appid": 614570,
      "url": "https://store.steampowered.com/app/614570/"
    },
    {
      "title": "Half-Life: Blue Shift",
      "steamName": "Half-Life: Blue Shift",
      "appid": 130,
      "url": "https://store.steampowered.com/app/130/"
    },
    {
      "title": "Half-Life: Opposing Force",
      "steamName": "Half-Life: Opposing Force",
      "appid": 50,
      "url": "https://store.steampowered.com/app/50/"
    },
    {
      "title": "Heroes of Might and Magic V: Tribes of the East",
      "steamName": "Heroes of Might & Magic V: Tribes of the East",
      "appid": 15370,
      "url": "https://store.steampowered.com/app/15370/"
    },
    {
      "title": "Mount & Blade: Warband",
      "steamName": "Mount & Blade: Warband",
      "appid": 48700,
      "url": "https://store.steampowered.com/app/48700/"
    },
    {
      "title": "Stronghold Crusader",
      "steamName": "Stronghold Crusader 2",
      "appid": 232890,
      "url": "https://store.steampowered.com/app/232890/"
    }
  ],
  "lowConfidence": []
}